README.rst
setup.py
fixers/__init__.py
fixers/fix_unicode.py
pyxform/__init__.py
pyxform/aliases.py
pyxform/builder.py
pyxform/constants.py
pyxform/errors.py
pyxform/file_utils.py
pyxform/instance.py
pyxform/models.py
pyxform/question.py
pyxform/question_type_dictionary.py
pyxform/section.py
pyxform/survey.py
pyxform/survey_element.py
pyxform/translator.py
pyxform/utils.py
pyxform/xform2json.py
pyxform/xform_instance_parser.py
pyxform/xls2json.py
pyxform/xls2json_backends.py
pyxform/xls2json_old.py
pyxform/xls2xform.py
pyxform/odk_validate/ODK_Validate.jar
pyxform/odk_validate/__init__.py
pyxform/tests/__init__.py
pyxform/tests/attribute_columns_test.py
pyxform/tests/bug_tests.py
pyxform/tests/builder_tests.py
pyxform/tests/dump_and_load_tests.py
pyxform/tests/file_utils_test.py
pyxform/tests/group_test.py
pyxform/tests/j2x_question_tests.py
pyxform/tests/j2x_test_creation.py
pyxform/tests/j2x_test_instantiation.py
pyxform/tests/j2x_test_xform_build_preparation.py
pyxform/tests/js2x_test_import_from_json.py
pyxform/tests/json2xform_test.py
pyxform/tests/loop_tests.py
pyxform/tests/new_cascading_select_test.py
pyxform/tests/odk_validate_tests.py
pyxform/tests/or_other_test.py
pyxform/tests/select_one_external_test.py
pyxform/tests/settings_test.py
pyxform/tests/test_file_type.py
pyxform/tests/test_osm.py
pyxform/tests/tests_by_file.py
pyxform/tests/tutorial_test.py
pyxform/tests/utils.py
pyxform/tests/xform2json_test.py
pyxform/tests/xls2json_tests.py
pyxform/tests/xls2xform_tests.py
pyxform/tests/xlsform_spec_test.py
pyxform/tests/xml_tests.py
pyxform/tests/bug_example_xls/ODKValidateWarnings.xlsx
pyxform/tests/bug_example_xls/badly_named_choices_sheet.xls
pyxform/tests/bug_example_xls/blank_second_row.xls
pyxform/tests/bug_example_xls/cascades_old.xls
pyxform/tests/bug_example_xls/cascades_old_with_no_cascade_sheet.xls
pyxform/tests/bug_example_xls/default_time_demo.xls
pyxform/tests/bug_example_xls/group_name_test.xls
pyxform_cadasta.egg-info/PKG-INFO
pyxform_cadasta.egg-info/SOURCES.txt
pyxform_cadasta.egg-info/dependency_links.txt
pyxform_cadasta.egg-info/requires.txt
pyxform_cadasta.egg-info/top_level.txt