Metadata-Version: 1.0
Name: pyxform-cadasta
Version: 0.9.22
Summary: A Python package to create XForms for ODK Collect.
Home-page: http://pypi.python.org/pypi/pyxform-cadasta/
Author: modilabs
Author-email: info@modilabs.org
License: UNKNOWN
Platform: UNKNOWN
